jiratag_commitizen/__init__.py
jiratag_commitizen/__main__.py
jiratag_commitizen/__version__.py
jiratag_commitizen/bump.py
jiratag_commitizen/cli.py
jiratag_commitizen/cmd.py
jiratag_commitizen/commands/__init__.py
jiratag_commitizen/commands/bump.py
jiratag_commitizen/commands/commit.py
jiratag_commitizen/commands/example.py
jiratag_commitizen/commands/info.py
jiratag_commitizen/commands/list_cz.py
jiratag_commitizen/commands/schema.py
jiratag_commitizen/config.py
jiratag_commitizen/cz/__init__.py
jiratag_commitizen/cz/base.py
jiratag_commitizen/cz/conventional_commits/__init__.py
jiratag_commitizen/cz/conventional_commits/conventional_commits.py
jiratag_commitizen/cz/conventional_commits/conventional_commits_info.txt
jiratag_commitizen/cz/jira/__init__.py
jiratag_commitizen/cz/jira/jira.py
jiratag_commitizen/cz/jira/jira_info.txt
jiratag_commitizen/defaults.py
jiratag_commitizen/factory.py
jiratag_commitizen/git.py
jiratag_commitizen/out.py
jiratag_commitizen-0.1.5.dist-info/entry_points.txt
jiratag_commitizen-0.1.5.dist-info/LICENSE
jiratag_commitizen-0.1.5.dist-info/WHEEL
jiratag_commitizen-0.1.5.dist-info/METADATA
jiratag_commitizen-0.1.5.dist-info/RECORD
